freetype/__init__.py
freetype/ft_errors.py
freetype/ft_structs.py
freetype/ft_types.py
freetype/libfreetype.dll
freetype/raw.py
freetype/ft_enums/__init__.py
freetype/ft_enums/ft_curve_tags.py
freetype/ft_enums/ft_encodings.py
freetype/ft_enums/ft_face_flags.py
freetype/ft_enums/ft_fstypes.py
freetype/ft_enums/ft_glyph_bbox_modes.py
freetype/ft_enums/ft_glyph_formats.py
freetype/ft_enums/ft_kerning_modes.py
freetype/ft_enums/ft_lcd_filters.py
freetype/ft_enums/ft_load_flags.py
freetype/ft_enums/ft_load_targets.py
freetype/ft_enums/ft_open_modes.py
freetype/ft_enums/ft_outline_flags.py
freetype/ft_enums/ft_pixel_modes.py
freetype/ft_enums/ft_render_modes.py
freetype/ft_enums/ft_stroker_borders.py
freetype/ft_enums/ft_stroker_linecaps.py
freetype/ft_enums/ft_stroker_linejoins.py
freetype/ft_enums/ft_style_flags.py
freetype/ft_enums/tt_adobe_ids.py
freetype/ft_enums/tt_apple_ids.py
freetype/ft_enums/tt_mac_ids.py
freetype/ft_enums/tt_mac_langids.py
freetype/ft_enums/tt_ms_ids.py
freetype/ft_enums/tt_ms_langids.py
freetype/ft_enums/tt_name_ids.py
freetype/ft_enums/tt_platforms.py
freetype_py-2.4.0.dist-info/LICENSE.txt
freetype_py-2.4.0.dist-info/METADATA
freetype_py-2.4.0.dist-info/WHEEL
freetype_py-2.4.0.dist-info/entry_points.txt
freetype_py-2.4.0.dist-info/top_level.txt
freetype_py-2.4.0.dist-info/RECORD
