Metadata-Version: 2.1
Name: freetype-py
Version: 2.4.0
Summary: Freetype python bindings
Home-page: https://github.com/rougier/freetype-py
Author: Nicolas P. Rougier
Author-email: Nicolas.Rougier@inria.fr
License: UNKNOWN
Keywords: freetype,font
Platform: UNKNOWN
Classifier: Development Status :: 5 - Production/Stable
Classifier: Environment :: X11 Applications
Classifier: Environment :: MacOS X
Classifier: Intended Audience :: Developers
Classifier: License :: OSI Approved :: BSD License
Classifier: Operating System :: MacOS
Classifier: Operating System :: Microsoft :: Windows
Classifier: Operating System :: POSIX
Classifier: Operating System :: Unix
Classifier: Programming Language :: Python :: 3
Classifier: Topic :: Multimedia :: Graphics
Requires-Python: >=3.7
License-File: LICENSE.txt
